<?xml version="1.0" encoding="UTF-8"?>
<!DOCTYPE shim SYSTEM "file:///usr/share/emane/dtd/shim.dtd">
<shim name="DLEPLAYER SHIM" library="emanelayerdlep">
  <paramlist name="macaddress">
    <item value="02 0a:B2:C3:D4:00:02"/>
  </paramlist>

  <param name="etheraddroui" value="00:00:02"/>
  <param name="sinrmin" value="0.0"/>
  <param name="sinrmax" value="20.0"/>

  <!-- dlep service config -->
  <param name="acktimeout"            value="3"/>
  <param name="ackprobability"         value="100"/>
  <param name="configfile"            value=""/>
  <param name="discoveryiface"        value="eth1"/>
  <param name="discoveryinterval"     value="5"/>
  <param name="discoverymcastaddress" value="224.0.0.117"/>
  <param name="discoveryport"         value="4854"/>
  <param name="discoveryenable"       value="1"/>

  <param name="destinationadvertenable"        value="1"/>
  <param name="destinationadvertiface"         value="eth0"/>
  <param name="destinationadvertsendinterval" value="5"/>
  <param name="destinationadvertmcastaddress" value="225.0.0.118"/>
  <param name="destinationadvertport"          value="5854"/>
  <param name="destinationadvertholdinterval" value="0"/>
  <param name="destinationadvertexpirecount"  value="0"/>

  <!--param name="experimentname"        value="rfpipe"/-->
  <param name="heartbeatinterval"     value="5"/>
  <param name="heartbeatthreshold"    value="2"/>
  <param name="localtype"             value="modem"/>
  <param name="loglevel"              value="1"/>
  <param name="logfile"               value="dlep2.log"/>
  <!--param name="metricfile"            value="metrics.xml"/-->
  <param name="peertype"              value="emane"/>
  <param name="sendtries"             value="3"/>
  <param name="sessionport"           value="4854"/>
  <param name="extensions"            value=""/>
  <param name="protocolconfigfile"    value="dlep-rfc-8175.xml"/>

</shim>

